join_asvbins/Snakefile
join_asvbins/__init__.py
join_asvbins/__main__.py
join_asvbins/snake_functions.py
join_asvbins/utils.py
join_asvbins/__pycache__/__init__.cpython-36.pyc
join_asvbins/__pycache__/__init__.cpython-37.pyc
join_asvbins/__pycache__/__init__.cpython-38.pyc
join_asvbins/__pycache__/__init__.cpython-39.pyc
join_asvbins/__pycache__/snake_functions.cpython-36.pyc
join_asvbins/__pycache__/snake_functions.cpython-39.pyc
join_asvbins/__pycache__/utils.cpython-36.pyc
join_asvbins/__pycache__/utils.cpython-39.pyc
join_asvbins/asvbin_joiner_rmflynn.egg-info/PKG-INFO
join_asvbins/asvbin_joiner_rmflynn.egg-info/SOURCES.txt
join_asvbins/asvbin_joiner_rmflynn.egg-info/dependency_links.txt
join_asvbins/asvbin_joiner_rmflynn.egg-info/requires.txt
join_asvbins/asvbin_joiner_rmflynn.egg-info/top_level.txt
join_asvbins-0.0.5.dist-info/LICENSE
join_asvbins-0.0.5.dist-info/METADATA
join_asvbins-0.0.5.dist-info/WHEEL
join_asvbins-0.0.5.dist-info/entry_points.txt
join_asvbins-0.0.5.dist-info/top_level.txt
join_asvbins-0.0.5.dist-info/RECORD
