Metadata-Version: 2.1
Name: join_asvbins
Version: 0.0.5
Summary: Asv to bin joining tool
Home-page: https://github.com/rmFlynn/16s_to_bins_project
Author: Rory Flynn
Author-email: Rory.Flynn@colostate.edu
License: UNKNOWN
Platform: UNKNOWN
Requires-Python: >=3
License-File: LICENSE
